[
  { "id": 1, "name": "Narra", "scientific_name": "Pterocarpus indicus" },
  { "id": 2, "name": "Mango", "scientific_name": "Mangifera indica" },
  { "id": 3, "name": "Mahogany", "scientific_name": "Swietenia macrophylla" },
  { "id": 4, "name": "Acacia", "scientific_name": "Samanea saman" },
  { "id": 5, "name": "Banana", "scientific_name": "Musa" },
  { "id": 6, "name": "Coconut", "scientific_name": "Cocos nucifera" },
  { "id": 7, "name": "Bamboo", "scientific_name": "Bambusoideae" },
  { "id": 8, "name": "Pine", "scientific_name": "Pinus" },
  { "id": 9, "name": "Gmelina", "scientific_name": "Gmelina arborea" },
  { "id": 10, "name": "Lanzones", "scientific_name": "Lansium parasiticum" },
  { "id": 11, "name": "Rambutan", "scientific_name": "Nephelium lappaceum" },
  { "id": 12, "name": "Duhat", "scientific_name": "Syzygium cumini" },
  { "id": 13, "name": "Sampalok", "scientific_name": "Tamarindus indica" },
  { "id": 14, "name": "Kamagong", "scientific_name": "Diospyros umbellata" },
  { "id": 15, "name": "Tugas", "scientific_name": "Vitex parviflora" },
  { "id": 16, "name": "Bignay", "scientific_name": "Antidesma bunius" },
  {
    "id": 17,
    "name": "Jackfruit",
    "scientific_name": "Artocarpus heterophyllus"
  },
  { "id": 18, "name": "Langka", "scientific_name": "Artocarpus heterophyllus" },
  { "id": 19, "name": "Banyan", "scientific_name": "Ficus benghalensis" },
  { "id": 20, "name": "Anahaw", "scientific_name": "Livistona rotundifolia" },
  { "id": 21, "name": "Red Maple", "scientific_name": "Acer rubrum" },
  { "id": 22, "name": "Oak", "scientific_name": "Quercus" },
  { "id": 23, "name": "White Ash", "scientific_name": "Fraxinus americana" },
  {
    "id": 24,
    "name": "Japanese Cherry",
    "scientific_name": "Prunus serrulata"
  },
  {
    "id": 25,
    "name": "American Sycamore",
    "scientific_name": "Platanus occidentalis"
  },
  { "id": 26, "name": "Black Walnut", "scientific_name": "Juglans nigra" },
  { "id": 27, "name": "Himalayan Cedar", "scientific_name": "Cedrus deodara" },
  { "id": 28, "name": "European Beech", "scientific_name": "Fagus sylvatica" },
  { "id": 29, "name": "Lemon Tree", "scientific_name": "Citrus limon" },
  { "id": 30, "name": "Olive Tree", "scientific_name": "Olea europaea" },
  { "id": 31, "name": "Pomegranate", "scientific_name": "Punica granatum" },
  { "id": 32, "name": "Bald Cypress", "scientific_name": "Taxodium distichum" },
  {
    "id": 33,
    "name": "Douglas Fir",
    "scientific_name": "Pseudotsuga menziesii"
  },
  { "id": 34, "name": "Western Red Cedar", "scientific_name": "Thuja plicata" },
  { "id": 35, "name": "Sugar Maple", "scientific_name": "Acer saccharum" },
  { "id": 36, "name": "Eucalyptus", "scientific_name": "Eucalyptus" },
  {
    "id": 37,
    "name": "Giant Sequoia",
    "scientific_name": "Sequoiadendron giganteum"
  },
  { "id": 38, "name": "Banyan Tree", "scientific_name": "Ficus benghalensis" },
  { "id": 39, "name": "Baobab", "scientific_name": "Adansonia" },
  { "id": 40, "name": "Cypress", "scientific_name": "Cupressus" },
  {
    "id": 41,
    "name": "Eastern White Pine",
    "scientific_name": "Pinus strobus"
  },
  { "id": 42, "name": "Scots Pine", "scientific_name": "Pinus sylvestris" },
  {
    "id": 43,
    "name": "Horse Chestnut",
    "scientific_name": "Aesculus hippocastanum"
  },
  { "id": 44, "name": "Norway Spruce", "scientific_name": "Picea abies" },
  { "id": 45, "name": "Cedar of Lebanon", "scientific_name": "Cedrus libani" },
  { "id": 46, "name": "Black Cherry", "scientific_name": "Prunus serotina" },
  { "id": 47, "name": "Cottonwood", "scientific_name": "Populus deltoides" },
  {
    "id": 48,
    "name": "Sweetgum",
    "scientific_name": "Liquidambar styraciflua"
  },
  { "id": 49, "name": "American Elm", "scientific_name": "Ulmus americana" },
  { "id": 50, "name": "Red Oak", "scientific_name": "Quercus rubra" },
  {
    "id": 51,
    "name": "Honey Locust",
    "scientific_name": "Gleditsia triacanthos"
  },
  { "id": 52, "name": "Weeping Willow", "scientific_name": "Salix babylonica" },
  {
    "id": 53,
    "name": "Quaking Aspen",
    "scientific_name": "Populus tremuloides"
  },
  { "id": 54, "name": "Pine Oak", "scientific_name": "Quercus palustris" },
  { "id": 55, "name": "White Birch", "scientific_name": "Betula papyrifera" },
  { "id": 56, "name": "Ginkgo", "scientific_name": "Ginkgo biloba" },
  {
    "id": 57,
    "name": "African Baobab",
    "scientific_name": "Adansonia digitata"
  },
  { "id": 58, "name": "Sandalwood", "scientific_name": "Santalum" },
  { "id": 59, "name": "Mangrove", "scientific_name": "Rhizophora" },
  {
    "id": 60,
    "name": "Norfolk Island Pine",
    "scientific_name": "Araucaria heterophylla"
  },
  { "id": 61, "name": "Rubber Tree", "scientific_name": "Hevea brasiliensis" },
  { "id": 62, "name": "Redwood", "scientific_name": "Sequoia sempervirens" },
  {
    "id": 63,
    "name": "Yellow Birch",
    "scientific_name": "Betula alleghaniensis"
  },
  { "id": 64, "name": "Silver Maple", "scientific_name": "Acer saccharinum" },
  { "id": 65, "name": "Chestnut", "scientific_name": "Castanea" },
  { "id": 66, "name": "Carob", "scientific_name": "Ceratonia siliqua" },
  { "id": 67, "name": "Alder", "scientific_name": "Alnus" },
  { "id": 68, "name": "White Ash", "scientific_name": "Fraxinus americana" },
  { "id": 69, "name": "Morus", "scientific_name": "Morus" },
  { "id": 70, "name": "Sassafras", "scientific_name": "Sassafras albidum" },
  { "id": 71, "name": "Elm", "scientific_name": "Ulmus" },
  { "id": 72, "name": "Persimmon", "scientific_name": "Diospyros" },
  { "id": 73, "name": "Tamarind", "scientific_name": "Tamarindus indica" },
  {
    "id": 74,
    "name": "Pineapple Guava",
    "scientific_name": "Feijoa sellowiana"
  },
  { "id": 75, "name": "Austrian Pine", "scientific_name": "Pinus nigra" },
  { "id": 76, "name": "Siberian Larch", "scientific_name": "Larix sibirica" },
  {
    "id": 77,
    "name": "Eastern Red Cedar",
    "scientific_name": "Juniperus virginiana"
  },
  { "id": 78, "name": "Willow Oak", "scientific_name": "Quercus phellos" },
  { "id": 79, "name": "Koa", "scientific_name": "Acacia koa" },
  { "id": 80, "name": "American Holly", "scientific_name": "Ilex opaca" },
  { "id": 81, "name": "Common Yew", "scientific_name": "Taxus baccata" },
  {
    "id": 82,
    "name": "Southern Magnolia",
    "scientific_name": "Magnolia grandiflora"
  },
  { "id": 83, "name": "Frangipani", "scientific_name": "Plumeria" },
  {
    "id": 84,
    "name": "Golden Rain Tree",
    "scientific_name": "Koelreuteria paniculata"
  },
  {
    "id": 85,
    "name": "Tropical Almond",
    "scientific_name": "Terminalia catappa"
  },
  { "id": 86, "name": "Red Mallee", "scientific_name": "Eucalyptus socialis" },
  {
    "id": 87,
    "name": "Australian Bottle Tree",
    "scientific_name": "Brachychiton populneus"
  },
  { "id": 88, "name": "Pecan", "scientific_name": "Carya illinoinensis" },
  { "id": 89, "name": "Spanish Cedar", "scientific_name": "Cedrela odorata" },
  { "id": 90, "name": "Saguaro", "scientific_name": "Carnegiea gigantea" },
  {
    "id": 91,
    "name": "Bottle Palm",
    "scientific_name": "Hyophorbe lagenicaulis"
  },
  { "id": 92, "name": "Foxtail Palm", "scientific_name": "Wodyetia bifurcata" },
  {
    "id": 93,
    "name": "Chilean Wine Palm",
    "scientific_name": "Jubaea chilensis"
  },
  { "id": 94, "name": "Coconut Palm", "scientific_name": "Cocos nucifera" },
  {
    "id": 95,
    "name": "Windmill Palm",
    "scientific_name": "Trachycarpus fortunei"
  },
  { "id": 96, "name": "Cabbage Palm", "scientific_name": "Sabal palmetto" },
  { "id": 97, "name": "Date Palm", "scientific_name": "Phoenix dactylifera" },
  {
    "id": 98,
    "name": "Queen Palm",
    "scientific_name": "Syagrus romanzoffiana"
  },
  { "id": 99, "name": "Caribbean Pine", "scientific_name": "Pinus caribaea" },
  { "id": 100, "name": "Australian Pine", "scientific_name": "Casuarina" },
  {
    "id": 101,
    "name": "Chinese Tallow Tree",
    "scientific_name": "Triadica sebifera"
  },
  {
    "id": 102,
    "name": "Chinese Scholar Tree",
    "scientific_name": "Sophora japonica"
  },
  { "id": 103, "name": "Chinese Elm", "scientific_name": "Ulmus parvifolia" },
  { "id": 104, "name": "Panda Tree", "scientific_name": "Panda" },
  { "id": 105, "name": "Coffee Tree", "scientific_name": "Coffea arabica" },
  { "id": 106, "name": "Chili Pepper Tree", "scientific_name": "Capsicum" },
  { "id": 107, "name": "Hawaiian Koa", "scientific_name": "Acacia koa" },
  {
    "id": 108,
    "name": "Black Locust",
    "scientific_name": "Robinia pseudoacacia"
  },
  { "id": 109, "name": "Sweet Chestnut", "scientific_name": "Castanea sativa" },
  {
    "id": 110,
    "name": "Indian Gooseberry",
    "scientific_name": "Phyllanthus emblica"
  }
]
